setup.py
xq_rpc/__init__.py
xq_rpc/client.py
xq_rpc/rpc.py
xq_rpc/rpc_pb2.py
xq_rpc/server.py
xq_rpc.egg-info/PKG-INFO
xq_rpc.egg-info/SOURCES.txt
xq_rpc.egg-info/dependency_links.txt
xq_rpc.egg-info/top_level.txt