Metadata-Version: 1.0
Name: xq-rpc
Version: 1.0.0.0
Summary: xq rpc
Home-page: UNKNOWN
Author: XQ
Author-email: 5273508@qq.com
License: MIT Licence
Keywords: pip,rpc
Platform: python 3.7
